dittto/__init__.py
dittto/autoencoder.py
dittto-1.0.0.dist-info/LICENSE
dittto-1.0.0.dist-info/METADATA
dittto-1.0.0.dist-info/WHEEL
dittto-1.0.0.dist-info/top_level.txt
dittto-1.0.0.dist-info/RECORD
